streaminput/__init__.py
streaminput/streaminput.py
StreamInput-0.0.1.dist-info/LICENSE
StreamInput-0.0.1.dist-info/METADATA
StreamInput-0.0.1.dist-info/WHEEL
StreamInput-0.0.1.dist-info/top_level.txt
StreamInput-0.0.1.dist-info/RECORD
